pyrsimg/__init__.py
pyrsimg/add_scale_north.py
pyrsimg/geo_imgxy.py
pyrsimg/img2patch.py
pyrsimg/imgShow.py
pyrsimg/img_normalize.py
pyrsimg/layer_stack.py
pyrsimg/metric_proc.py
pyrsimg/metrics.py
pyrsimg/raster_vec.py
pyrsimg/rsimg_io-deprecated.py
pyrsimg/transform_time.py
pyrsimg-1.1.4.dist-info/METADATA
pyrsimg-1.1.4.dist-info/WHEEL
pyrsimg-1.1.4.dist-info/top_level.txt
pyrsimg-1.1.4.dist-info/RECORD
