Metadata-Version: 2.4
Name: pyrsimg
Version: 1.1.4
Summary: Python toolkit for easy processing of satellite image
Author: The pyrsimg developers
Author-email: xinluo_xin@163.com
Maintainer: Xin Luo
Maintainer-email: xinluo_xin@163.com
License: GPL License
Requires-Python: >=3.8
Requires-Dist: scikit-learn
Requires-Dist: numpy
Requires-Dist: opencv-python
Requires-Dist: matplotlib
Requires-Dist: scipy
Requires-Dist: geopandas
Requires-Dist: rasterio
Requires-Dist: cartopy
Requires-Dist: astropy
Dynamic: author
Dynamic: author-email
Dynamic: license
Dynamic: maintainer
Dynamic: maintainer-email
Dynamic: requires-dist
Dynamic: requires-python
Dynamic: summary
